epistolary/__init__.py
epistolary/orchestrator.py
epistolary/types.py
epistolary/cli/__init__.py
epistolary/document_manager/__init__.py
epistolary/document_manager/document_manager.py
epistolary/document_manager/filesystem_document_manager.py
epistolary/document_manager/remarkable_document_manager.py
epistolary/epiconfig/__init__.py
epistolary/mailbox_manager/__init__.py
epistolary/mailbox_manager/mailbox_manager.py
epistolary/mailbox_manager/smtpimap_mailbox_manager.py
epistolary/remarkable/__init__.py
epistolary/text_extractor/__init__.py
epistolary/text_extractor/openai_text_extractor.py
epistolary/text_extractor/tesseract_text_extractor.py
epistolary/text_extractor/text_extractor.py
epistolary-0.2.0.dist-info/METADATA
epistolary-0.2.0.dist-info/WHEEL
epistolary-0.2.0.dist-info/entry_points.txt
epistolary-0.2.0.dist-info/licenses/LICENSE
epistolary-0.2.0.dist-info/RECORD
