Metadata-Version: 2.3
Name: epistolary
Version: 0.2.0
Summary: Add your description here
License-File: LICENSE
Requires-Python: >=3.11
Requires-Dist: boto3>=1.35.8
Requires-Dist: click>=8.1.7
Requires-Dist: openai>=1.43.0
Requires-Dist: pillow>=10.4.0
Requires-Dist: pytesseract>=0.3.13
Requires-Dist: redbox>=0.2.1
Requires-Dist: redmail>=0.6.0
Requires-Dist: remarks
